ellippy-1.0.1.dist-info/METADATA
ellippy-1.0.1.dist-info/WHEEL
ellippy-1.0.1.dist-info/licenses/LICENSE
ellippy/__about__.py
ellippy/__init__.py
ellippy/_ellip.py
ellippy/bulirsch.py
ellippy/carlson.py
ellippy/ellippy_binding.cp312-win_amd64.pyd
ellippy/legendre.py
ellippy/misc.py
ellippy-1.0.1.dist-info/RECORD
