Metadata-Version: 2.4
Name: ellippy
Version: 1.0.1
Classifier: Programming Language :: Python :: 3
Classifier: License :: OSI Approved :: BSD License
Classifier: Operating System :: OS Independent
Requires-Dist: maturin>=1.9.4
Requires-Dist: numpy>=2.2.6
License-File: LICENSE
Summary: An elliptic integral library for Python
Home-Page: https://github.com/p-sira/ellippy
Author-email: Sira Pornsiriprasert <code@psira.me>
Maintainer-email: Sira Pornsiriprasert <code@psira.me>
Requires-Python: >=3.10
Project-URL: Homepage, https://github.com/p-sira/ellippy
Project-URL: Repository, https://github.com/p-sira/ellippy
Project-URL: Issues, https://github.com/p-sira/ellippy/issues
Project-URL: Documentation, https://p-sira.github.io/ellippy/
